pillory.py
pillory-2.0.0.dist-info/LICENSE
pillory-2.0.0.dist-info/WHEEL
pillory-2.0.0.dist-info/METADATA
pillory-2.0.0.dist-info/RECORD
