Metadata-Version: 2.1
Name: pillory
Version: 2.0.0
Summary: A linter to scrutinize how you are using mocks in Python.
Author-email: Fergal Armstrong <patio.algebra0i@icloud.com>
Classifier: License :: OSI Approved :: Apache Software License
Requires-Dist: coverage~=7.5 ; extra == "dev"
Requires-Dist: flit~=3.9 ; extra == "dev"
Requires-Dist: pip-tools~=7.4 ; extra == "dev"
Requires-Dist: pre-commit~=3.7 ; extra == "dev"
Requires-Dist: ruff~=0.3 ; extra == "dev"
Project-URL: Home, https://github.com/fffergal/pillory
Provides-Extra: dev
